LICENSE
MANIFEST.in
README.rst
setup.py
btc_report_designer.egg-info/PKG-INFO
btc_report_designer.egg-info/SOURCES.txt
btc_report_designer.egg-info/dependency_links.txt
btc_report_designer.egg-info/requires.txt
btc_report_designer.egg-info/top_level.txt
report_designer/__init__.py
report_designer/admin.py
report_designer/apps.py
report_designer/builder.py
report_designer/consts.py
report_designer/managers.py
report_designer/models.py
report_designer/tests.py
report_designer/urls.py
report_designer/views.py
report_designer/core/__init__.py
report_designer/core/actions.py
report_designer/core/breadcrumbs.py
report_designer/core/filters.py
report_designer/core/forms.py
report_designer/core/formsets.py
report_designer/core/joiner.py
report_designer/core/tables.py
report_designer/core/utils.py
report_designer/core/views.py
report_designer/formats/__init__.py
report_designer/formats/actions.py
report_designer/formats/filters.py
report_designer/formats/forms.py
report_designer/formats/tables.py
report_designer/formats/urls.py
report_designer/formats/views.py
report_designer/groups/__init__.py
report_designer/groups/actions.py
report_designer/groups/filters.py
report_designer/groups/forms.py
report_designer/groups/tables.py
report_designer/groups/urls.py
report_designer/groups/views.py
report_designer/migrations/0001_initial.py
report_designer/migrations/0002_auto_20210831_1750.py
report_designer/migrations/0003_auto_20211006_1159.py
report_designer/migrations/0004_auto_20211019_1518.py
report_designer/migrations/0005_auto_20211026_1805.py
report_designer/migrations/0006_auto_20211026_1925.py
report_designer/migrations/0007_auto_20211027_1539.py
report_designer/migrations/0008_remove_report_tables.py
report_designer/migrations/0009_reporttablerelation_reporttablerelationcondition.py
report_designer/migrations/0010_reportfield_report_table_relation.py
report_designer/migrations/0011_auto_20211105_1956.py
report_designer/migrations/__init__.py
report_designer/reports/__init__.py
report_designer/reports/actions.py
report_designer/reports/filters.py
report_designer/reports/forms.py
report_designer/reports/report_handler.py
report_designer/reports/tables.py
