Metadata-Version: 1.1
Name: btc-report-designer
Version: 0.1.18
Summary: An application for creating reports based django models.
Home-page: UNKNOWN
Author: Pavel Boichenko
Author-email: nuchimik@gmail.com
License: BSD License
Platform: UNKNOWN
Classifier: Environment :: Web Environment
Classifier: Framework :: Django
Classifier: Intended Audience :: Developers
Classifier: License :: OSI Approved :: BSD License
Classifier: Operating System :: OS Independent
Classifier: Programming Language :: Python :: 3.6
Classifier: Topic :: Internet :: WWW/HTTP
Classifier: Topic :: Internet :: WWW/HTTP :: Dynamic Content
